{
  "id": {
    "address": "contract_v3",
    "name": "events"
  },
  "doc": " Events module for Love Letter with Seal Integration\n All game events for frontend tracking",
  "immediate_dependencies": [
    {
      "address": "std",
      "name": "option"
    },
    {
      "address": "std",
      "name": "string"
    },
    {
      "address": "sui",
      "name": "event"
    },
    {
      "address": "sui",
      "name": "object"
    }
  ],
  "attributes": [],
  "functions": {
    "emit_room_created": {
      "source_index": 0,
      "index": 0,
      "doc": null,
      "attributes": [],
      "visibility": "Public",
      "entry": false,
      "type_parameters": [],
      "parameters": [
        {
          "name": "room_id",
          "type_": {
            "Datatype": {
              "module": {
                "address": "sui",
                "name": "object"
              },
              "name": "ID",
              "type_arguments": []
            }
          }
        },
        {
          "name": "creator",
          "type_": "address"
        },
        {
          "name": "name",
          "type_": {
            "Datatype": {
              "module": {
                "address": "std",
                "name": "string"
              },
              "name": "String",
              "type_arguments": []
            }
          }
        },
        {
          "name": "max_players",
          "type_": "u8"
        },
        {
          "name": "entry_fee",
          "type_": "u64"
        },
        {
          "name": "tokens_to_win",
          "type_": "u8"
        }
      ],
      "return_": []
    },
    "emit_player_joined": {
      "source_index": 1,
      "index": 1,
      "doc": null,
      "attributes": [],
      "visibility": "Public",
      "entry": false,
      "type_parameters": [],
      "parameters": [
        {
          "name": "room_id",
          "type_": {
            "Datatype": {
              "module": {
                "address": "sui",
                "name": "object"
              },
              "name": "ID",
              "type_arguments": []
            }
          }
        },
        {
          "name": "player",
          "type_": "address"
        },
        {
          "name": "current_players",
          "type_": "u8"
        },
        {
          "name": "max_players",
          "type_": "u8"
        }
      ],
      "return_": []
    },
    "emit_round_started": {
      "source_index": 2,
      "index": 2,
      "doc": null,
      "attributes": [],
      "visibility": "Public",
      "entry": false,
      "type_parameters": [],
      "parameters": [
        {
          "name": "room_id",
          "type_": {
            "Datatype": {
              "module": {
                "address": "sui",
                "name": "object"
              },
              "name": "ID",
              "type_arguments": []
            }
          }
        },
        {
          "name": "round_number",
          "type_": "u8"
        },
        {
          "name": "players",
          "type_": {
            "vector": "address"
          }
        },
        {
          "name": "first_player",
          "type_": "address"
        },
        {
          "name": "public_cards",
          "type_": {
            "vector": "u8"
          }
        },
        {
          "name": "dealt_card_indices",
          "type_": {
            "vector": {
              "vector": "u64"
            }
          }
        }
      ],
      "return_": []
    },
    "emit_round_ended": {
      "source_index": 3,
      "index": 3,
      "doc": null,
      "attributes": [],
      "visibility": "Public",
      "entry": false,
      "type_parameters": [],
      "parameters": [
        {
          "name": "room_id",
          "type_": {
            "Datatype": {
              "module": {
                "address": "sui",
                "name": "object"
              },
              "name": "ID",
              "type_arguments": []
            }
          }
        },
        {
          "name": "round_number",
          "type_": "u8"
        },
        {
          "name": "winner",
          "type_": "address"
        },
        {
          "name": "winning_card",
          "type_": "u8"
        },
        {
          "name": "spy_bonus_player",
          "type_": {
            "Datatype": {
              "module": {
                "address": "std",
                "name": "option"
              },
              "name": "Option",
              "type_arguments": [
                {
                  "phantom": false,
                  "argument": "address"
                }
              ]
            }
          }
        }
      ],
      "return_": []
    },
    "emit_turn_played": {
      "source_index": 4,
      "index": 4,
      "doc": null,
      "attributes": [],
      "visibility": "Public",
      "entry": false,
      "type_parameters": [],
      "parameters": [
        {
          "name": "room_id",
          "type_": {
            "Datatype": {
              "module": {
                "address": "sui",
                "name": "object"
              },
              "name": "ID",
              "type_arguments": []
            }
          }
        },
        {
          "name": "player",
          "type_": "address"
        },
        {
          "name": "card_played",
          "type_": "u8"
        },
        {
          "name": "target",
          "type_": {
            "Datatype": {
              "module": {
                "address": "std",
                "name": "option"
              },
              "name": "Option",
              "type_arguments": [
                {
                  "phantom": false,
                  "argument": "address"
                }
              ]
            }
          }
        },
        {
          "name": "guess",
          "type_": {
            "Datatype": {
              "module": {
                "address": "std",
                "name": "option"
              },
              "name": "Option",
              "type_arguments": [
                {
                  "phantom": false,
                  "argument": "u8"
                }
              ]
            }
          }
        },
        {
          "name": "result",
          "type_": {
            "Datatype": {
              "module": {
                "address": "std",
                "name": "string"
              },
              "name": "String",
              "type_arguments": []
            }
          }
        }
      ],
      "return_": []
    },
    "emit_turn_advanced": {
      "source_index": 5,
      "index": 5,
      "doc": null,
      "attributes": [],
      "visibility": "Public",
      "entry": false,
      "type_parameters": [],
      "parameters": [
        {
          "name": "room_id",
          "type_": {
            "Datatype": {
              "module": {
                "address": "sui",
                "name": "object"
              },
              "name": "ID",
              "type_arguments": []
            }
          }
        },
        {
          "name": "next_player",
          "type_": "address"
        },
        {
          "name": "new_card_index",
          "type_": "u64"
        }
      ],
      "return_": []
    },
    "emit_player_eliminated": {
      "source_index": 6,
      "index": 6,
      "doc": null,
      "attributes": [],
      "visibility": "Public",
      "entry": false,
      "type_parameters": [],
      "parameters": [
        {
          "name": "room_id",
          "type_": {
            "Datatype": {
              "module": {
                "address": "sui",
                "name": "object"
              },
              "name": "ID",
              "type_arguments": []
            }
          }
        },
        {
          "name": "eliminated",
          "type_": "address"
        },
        {
          "name": "eliminated_by",
          "type_": "address"
        },
        {
          "name": "card_used",
          "type_": "u8"
        },
        {
          "name": "revealed_hand",
          "type_": {
            "vector": "u8"
          }
        }
      ],
      "return_": []
    },
    "emit_card_revealed": {
      "source_index": 7,
      "index": 7,
      "doc": null,
      "attributes": [],
      "visibility": "Public",
      "entry": false,
      "type_parameters": [],
      "parameters": [
        {
          "name": "room_id",
          "type_": {
            "Datatype": {
              "module": {
                "address": "sui",
                "name": "object"
              },
              "name": "ID",
              "type_arguments": []
            }
          }
        },
        {
          "name": "viewer",
          "type_": "address"
        },
        {
          "name": "target",
          "type_": "address"
        },
        {
          "name": "card_index",
          "type_": "u64"
        },
        {
          "name": "access_expires_turn",
          "type_": "u64"
        }
      ],
      "return_": []
    },
    "emit_baron_comparison": {
      "source_index": 8,
      "index": 8,
      "doc": null,
      "attributes": [],
      "visibility": "Public",
      "entry": false,
      "type_parameters": [],
      "parameters": [
        {
          "name": "room_id",
          "type_": {
            "Datatype": {
              "module": {
                "address": "sui",
                "name": "object"
              },
              "name": "ID",
              "type_arguments": []
            }
          }
        },
        {
          "name": "attacker",
          "type_": "address"
        },
        {
          "name": "attacker_card",
          "type_": "u8"
        },
        {
          "name": "defender",
          "type_": "address"
        },
        {
          "name": "defender_card",
          "type_": "u8"
        },
        {
          "name": "loser",
          "type_": {
            "Datatype": {
              "module": {
                "address": "std",
                "name": "option"
              },
              "name": "Option",
              "type_arguments": [
                {
                  "phantom": false,
                  "argument": "address"
                }
              ]
            }
          }
        }
      ],
      "return_": []
    },
    "emit_hands_swapped": {
      "source_index": 9,
      "index": 9,
      "doc": null,
      "attributes": [],
      "visibility": "Public",
      "entry": false,
      "type_parameters": [],
      "parameters": [
        {
          "name": "room_id",
          "type_": {
            "Datatype": {
              "module": {
                "address": "sui",
                "name": "object"
              },
              "name": "ID",
              "type_arguments": []
            }
          }
        },
        {
          "name": "player1",
          "type_": "address"
        },
        {
          "name": "player2",
          "type_": "address"
        },
        {
          "name": "player1_new_card_index",
          "type_": "u64"
        },
        {
          "name": "player2_new_card_index",
          "type_": "u64"
        }
      ],
      "return_": []
    },
    "emit_chancellor_draw": {
      "source_index": 10,
      "index": 10,
      "doc": null,
      "attributes": [],
      "visibility": "Public",
      "entry": false,
      "type_parameters": [],
      "parameters": [
        {
          "name": "room_id",
          "type_": {
            "Datatype": {
              "module": {
                "address": "sui",
                "name": "object"
              },
              "name": "ID",
              "type_arguments": []
            }
          }
        },
        {
          "name": "player",
          "type_": "address"
        },
        {
          "name": "drawn_card_indices",
          "type_": {
            "vector": "u64"
          }
        }
      ],
      "return_": []
    },
    "emit_chancellor_resolved": {
      "source_index": 11,
      "index": 11,
      "doc": null,
      "attributes": [],
      "visibility": "Public",
      "entry": false,
      "type_parameters": [],
      "parameters": [
        {
          "name": "room_id",
          "type_": {
            "Datatype": {
              "module": {
                "address": "sui",
                "name": "object"
              },
              "name": "ID",
              "type_arguments": []
            }
          }
        },
        {
          "name": "player",
          "type_": "address"
        },
        {
          "name": "kept_card_index",
          "type_": "u64"
        },
        {
          "name": "returned_count",
          "type_": "u64"
        }
      ],
      "return_": []
    },
    "emit_pending_guard_response": {
      "source_index": 12,
      "index": 12,
      "doc": null,
      "attributes": [],
      "visibility": "Public",
      "entry": false,
      "type_parameters": [],
      "parameters": [
        {
          "name": "room_id",
          "type_": {
            "Datatype": {
              "module": {
                "address": "sui",
                "name": "object"
              },
              "name": "ID",
              "type_arguments": []
            }
          }
        },
        {
          "name": "attacker",
          "type_": "address"
        },
        {
          "name": "target",
          "type_": "address"
        },
        {
          "name": "guess",
          "type_": "u8"
        }
      ],
      "return_": []
    },
    "emit_pending_baron_response": {
      "source_index": 13,
      "index": 13,
      "doc": null,
      "attributes": [],
      "visibility": "Public",
      "entry": false,
      "type_parameters": [],
      "parameters": [
        {
          "name": "room_id",
          "type_": {
            "Datatype": {
              "module": {
                "address": "sui",
                "name": "object"
              },
              "name": "ID",
              "type_arguments": []
            }
          }
        },
        {
          "name": "attacker",
          "type_": "address"
        },
        {
          "name": "attacker_card",
          "type_": "u8"
        },
        {
          "name": "target",
          "type_": "address"
        }
      ],
      "return_": []
    },
    "emit_guard_response": {
      "source_index": 14,
      "index": 14,
      "doc": null,
      "attributes": [],
      "visibility": "Public",
      "entry": false,
      "type_parameters": [],
      "parameters": [
        {
          "name": "room_id",
          "type_": {
            "Datatype": {
              "module": {
                "address": "sui",
                "name": "object"
              },
              "name": "ID",
              "type_arguments": []
            }
          }
        },
        {
          "name": "target",
          "type_": "address"
        },
        {
          "name": "revealed_card",
          "type_": "u8"
        },
        {
          "name": "guess_correct",
          "type_": "bool"
        }
      ],
      "return_": []
    },
    "emit_token_awarded": {
      "source_index": 15,
      "index": 15,
      "doc": null,
      "attributes": [],
      "visibility": "Public",
      "entry": false,
      "type_parameters": [],
      "parameters": [
        {
          "name": "room_id",
          "type_": {
            "Datatype": {
              "module": {
                "address": "sui",
                "name": "object"
              },
              "name": "ID",
              "type_arguments": []
            }
          }
        },
        {
          "name": "player",
          "type_": "address"
        },
        {
          "name": "total_tokens",
          "type_": "u8"
        },
        {
          "name": "reason",
          "type_": {
            "Datatype": {
              "module": {
                "address": "std",
                "name": "string"
              },
              "name": "String",
              "type_arguments": []
            }
          }
        }
      ],
      "return_": []
    },
    "emit_spy_bonus_check": {
      "source_index": 16,
      "index": 16,
      "doc": null,
      "attributes": [],
      "visibility": "Public",
      "entry": false,
      "type_parameters": [],
      "parameters": [
        {
          "name": "room_id",
          "type_": {
            "Datatype": {
              "module": {
                "address": "sui",
                "name": "object"
              },
              "name": "ID",
              "type_arguments": []
            }
          }
        },
        {
          "name": "players_with_spy",
          "type_": {
            "vector": "address"
          }
        },
        {
          "name": "bonus_awarded",
          "type_": "bool"
        },
        {
          "name": "bonus_recipient",
          "type_": {
            "Datatype": {
              "module": {
                "address": "std",
                "name": "option"
              },
              "name": "Option",
              "type_arguments": [
                {
                  "phantom": false,
                  "argument": "address"
                }
              ]
            }
          }
        }
      ],
      "return_": []
    },
    "emit_game_ended": {
      "source_index": 17,
      "index": 17,
      "doc": null,
      "attributes": [],
      "visibility": "Public",
      "entry": false,
      "type_parameters": [],
      "parameters": [
        {
          "name": "room_id",
          "type_": {
            "Datatype": {
              "module": {
                "address": "sui",
                "name": "object"
              },
              "name": "ID",
              "type_arguments": []
            }
          }
        },
        {
          "name": "winner",
          "type_": "address"
        },
        {
          "name": "final_tokens",
          "type_": "u8"
        },
        {
          "name": "prize_pool",
          "type_": "u64"
        },
        {
          "name": "total_rounds",
          "type_": "u8"
        }
      ],
      "return_": []
    },
    "emit_commitment_created": {
      "source_index": 18,
      "index": 18,
      "doc": null,
      "attributes": [],
      "visibility": "Public",
      "entry": false,
      "type_parameters": [],
      "parameters": [
        {
          "name": "room_id",
          "type_": {
            "Datatype": {
              "module": {
                "address": "sui",
                "name": "object"
              },
              "name": "ID",
              "type_arguments": []
            }
          }
        },
        {
          "name": "card_index",
          "type_": "u64"
        },
        {
          "name": "commitment",
          "type_": {
            "vector": "u8"
          }
        }
      ],
      "return_": []
    },
    "emit_commitment_verified": {
      "source_index": 19,
      "index": 19,
      "doc": null,
      "attributes": [],
      "visibility": "Public",
      "entry": false,
      "type_parameters": [],
      "parameters": [
        {
          "name": "room_id",
          "type_": {
            "Datatype": {
              "module": {
                "address": "sui",
                "name": "object"
              },
              "name": "ID",
              "type_arguments": []
            }
          }
        },
        {
          "name": "card_index",
          "type_": "u64"
        },
        {
          "name": "revealed_value",
          "type_": "u8"
        },
        {
          "name": "verified",
          "type_": "bool"
        }
      ],
      "return_": []
    },
    "emit_temporary_access_granted": {
      "source_index": 20,
      "index": 20,
      "doc": null,
      "attributes": [],
      "visibility": "Public",
      "entry": false,
      "type_parameters": [],
      "parameters": [
        {
          "name": "room_id",
          "type_": {
            "Datatype": {
              "module": {
                "address": "sui",
                "name": "object"
              },
              "name": "ID",
              "type_arguments": []
            }
          }
        },
        {
          "name": "viewer",
          "type_": "address"
        },
        {
          "name": "card_index",
          "type_": "u64"
        },
        {
          "name": "expires_turn",
          "type_": "u64"
        }
      ],
      "return_": []
    }
  },
  "structs": {
    "RoomCreated": {
      "index": 0,
      "doc": null,
      "attributes": [],
      "abilities": [
        "Copy",
        "Drop"
      ],
      "type_parameters": [],
      "fields": {
        "positional_fields": false,
        "fields": {
          "room_id": {
            "index": 0,
            "doc": null,
            "type_": {
              "Datatype": {
                "module": {
                  "address": "sui",
                  "name": "object"
                },
                "name": "ID",
                "type_arguments": []
              }
            }
          },
          "creator": {
            "index": 1,
            "doc": null,
            "type_": "address"
          },
          "name": {
            "index": 2,
            "doc": null,
            "type_": {
              "Datatype": {
                "module": {
                  "address": "std",
                  "name": "string"
                },
                "name": "String",
                "type_arguments": []
              }
            }
          },
          "max_players": {
            "index": 3,
            "doc": null,
            "type_": "u8"
          },
          "entry_fee": {
            "index": 4,
            "doc": null,
            "type_": "u64"
          },
          "tokens_to_win": {
            "index": 5,
            "doc": null,
            "type_": "u8"
          }
        }
      }
    },
    "PlayerJoined": {
      "index": 1,
      "doc": null,
      "attributes": [],
      "abilities": [
        "Copy",
        "Drop"
      ],
      "type_parameters": [],
      "fields": {
        "positional_fields": false,
        "fields": {
          "room_id": {
            "index": 0,
            "doc": null,
            "type_": {
              "Datatype": {
                "module": {
                  "address": "sui",
                  "name": "object"
                },
                "name": "ID",
                "type_arguments": []
              }
            }
          },
          "player": {
            "index": 1,
            "doc": null,
            "type_": "address"
          },
          "current_players": {
            "index": 2,
            "doc": null,
            "type_": "u8"
          },
          "max_players": {
            "index": 3,
            "doc": null,
            "type_": "u8"
          }
        }
      }
    },
    "RoundStarted": {
      "index": 2,
      "doc": null,
      "attributes": [],
      "abilities": [
        "Copy",
        "Drop"
      ],
      "type_parameters": [],
      "fields": {
        "positional_fields": false,
        "fields": {
          "room_id": {
            "index": 0,
            "doc": null,
            "type_": {
              "Datatype": {
                "module": {
                  "address": "sui",
                  "name": "object"
                },
                "name": "ID",
                "type_arguments": []
              }
            }
          },
          "round_number": {
            "index": 1,
            "doc": null,
            "type_": "u8"
          },
          "players": {
            "index": 2,
            "doc": null,
            "type_": {
              "vector": "address"
            }
          },
          "first_player": {
            "index": 3,
            "doc": null,
            "type_": "address"
          },
          "public_cards": {
            "index": 4,
            "doc": null,
            "type_": {
              "vector": "u8"
            }
          },
          "dealt_card_indices": {
            "index": 5,
            "doc": " Card indices dealt to each player (encrypted values stored separately)",
            "type_": {
              "vector": {
                "vector": "u64"
              }
            }
          }
        }
      }
    },
    "RoundEnded": {
      "index": 3,
      "doc": null,
      "attributes": [],
      "abilities": [
        "Copy",
        "Drop"
      ],
      "type_parameters": [],
      "fields": {
        "positional_fields": false,
        "fields": {
          "room_id": {
            "index": 0,
            "doc": null,
            "type_": {
              "Datatype": {
                "module": {
                  "address": "sui",
                  "name": "object"
                },
                "name": "ID",
                "type_arguments": []
              }
            }
          },
          "round_number": {
            "index": 1,
            "doc": null,
            "type_": "u8"
          },
          "winner": {
            "index": 2,
            "doc": null,
            "type_": "address"
          },
          "winning_card": {
            "index": 3,
            "doc": null,
            "type_": "u8"
          },
          "spy_bonus_player": {
            "index": 4,
            "doc": null,
            "type_": {
              "Datatype": {
                "module": {
                  "address": "std",
                  "name": "option"
                },
                "name": "Option",
                "type_arguments": [
                  {
                    "phantom": false,
                    "argument": "address"
                  }
                ]
              }
            }
          }
        }
      }
    },
    "TurnPlayed": {
      "index": 4,
      "doc": null,
      "attributes": [],
      "abilities": [
        "Copy",
        "Drop"
      ],
      "type_parameters": [],
      "fields": {
        "positional_fields": false,
        "fields": {
          "room_id": {
            "index": 0,
            "doc": null,
            "type_": {
              "Datatype": {
                "module": {
                  "address": "sui",
                  "name": "object"
                },
                "name": "ID",
                "type_arguments": []
              }
            }
          },
          "player": {
            "index": 1,
            "doc": null,
            "type_": "address"
          },
          "card_played": {
            "index": 2,
            "doc": null,
            "type_": "u8"
          },
          "target": {
            "index": 3,
            "doc": null,
            "type_": {
              "Datatype": {
                "module": {
                  "address": "std",
                  "name": "option"
                },
                "name": "Option",
                "type_arguments": [
                  {
                    "phantom": false,
                    "argument": "address"
                  }
                ]
              }
            }
          },
          "guess": {
            "index": 4,
            "doc": null,
            "type_": {
              "Datatype": {
                "module": {
                  "address": "std",
                  "name": "option"
                },
                "name": "Option",
                "type_arguments": [
                  {
                    "phantom": false,
                    "argument": "u8"
                  }
                ]
              }
            }
          },
          "result": {
            "index": 5,
            "doc": null,
            "type_": {
              "Datatype": {
                "module": {
                  "address": "std",
                  "name": "string"
                },
                "name": "String",
                "type_arguments": []
              }
            }
          }
        }
      }
    },
    "TurnAdvanced": {
      "index": 5,
      "doc": null,
      "attributes": [],
      "abilities": [
        "Copy",
        "Drop"
      ],
      "type_parameters": [],
      "fields": {
        "positional_fields": false,
        "fields": {
          "room_id": {
            "index": 0,
            "doc": null,
            "type_": {
              "Datatype": {
                "module": {
                  "address": "sui",
                  "name": "object"
                },
                "name": "ID",
                "type_arguments": []
              }
            }
          },
          "next_player": {
            "index": 1,
            "doc": null,
            "type_": "address"
          },
          "new_card_index": {
            "index": 2,
            "doc": null,
            "type_": "u64"
          }
        }
      }
    },
    "PlayerEliminated": {
      "index": 6,
      "doc": null,
      "attributes": [],
      "abilities": [
        "Copy",
        "Drop"
      ],
      "type_parameters": [],
      "fields": {
        "positional_fields": false,
        "fields": {
          "room_id": {
            "index": 0,
            "doc": null,
            "type_": {
              "Datatype": {
                "module": {
                  "address": "sui",
                  "name": "object"
                },
                "name": "ID",
                "type_arguments": []
              }
            }
          },
          "eliminated": {
            "index": 1,
            "doc": null,
            "type_": "address"
          },
          "eliminated_by": {
            "index": 2,
            "doc": null,
            "type_": "address"
          },
          "card_used": {
            "index": 3,
            "doc": null,
            "type_": "u8"
          },
          "revealed_hand": {
            "index": 4,
            "doc": null,
            "type_": {
              "vector": "u8"
            }
          }
        }
      }
    },
    "CardRevealed": {
      "index": 7,
      "doc": " Priest effect - card revealed to specific player only",
      "attributes": [],
      "abilities": [
        "Copy",
        "Drop"
      ],
      "type_parameters": [],
      "fields": {
        "positional_fields": false,
        "fields": {
          "room_id": {
            "index": 0,
            "doc": null,
            "type_": {
              "Datatype": {
                "module": {
                  "address": "sui",
                  "name": "object"
                },
                "name": "ID",
                "type_arguments": []
              }
            }
          },
          "viewer": {
            "index": 1,
            "doc": null,
            "type_": "address"
          },
          "target": {
            "index": 2,
            "doc": null,
            "type_": "address"
          },
          "card_index": {
            "index": 3,
            "doc": null,
            "type_": "u64"
          },
          "access_expires_turn": {
            "index": 4,
            "doc": " Access granted until this turn number",
            "type_": "u64"
          }
        }
      }
    },
    "BaronComparison": {
      "index": 8,
      "doc": " Baron comparison result",
      "attributes": [],
      "abilities": [
        "Copy",
        "Drop"
      ],
      "type_parameters": [],
      "fields": {
        "positional_fields": false,
        "fields": {
          "room_id": {
            "index": 0,
            "doc": null,
            "type_": {
              "Datatype": {
                "module": {
                  "address": "sui",
                  "name": "object"
                },
                "name": "ID",
                "type_arguments": []
              }
            }
          },
          "attacker": {
            "index": 1,
            "doc": null,
            "type_": "address"
          },
          "attacker_card": {
            "index": 2,
            "doc": null,
            "type_": "u8"
          },
          "defender": {
            "index": 3,
            "doc": null,
            "type_": "address"
          },
          "defender_card": {
            "index": 4,
            "doc": null,
            "type_": "u8"
          },
          "loser": {
            "index": 5,
            "doc": null,
            "type_": {
              "Datatype": {
                "module": {
                  "address": "std",
                  "name": "option"
                },
                "name": "Option",
                "type_arguments": [
                  {
                    "phantom": false,
                    "argument": "address"
                  }
                ]
              }
            }
          }
        }
      }
    },
    "HandsSwapped": {
      "index": 9,
      "doc": " King swap",
      "attributes": [],
      "abilities": [
        "Copy",
        "Drop"
      ],
      "type_parameters": [],
      "fields": {
        "positional_fields": false,
        "fields": {
          "room_id": {
            "index": 0,
            "doc": null,
            "type_": {
              "Datatype": {
                "module": {
                  "address": "sui",
                  "name": "object"
                },
                "name": "ID",
                "type_arguments": []
              }
            }
          },
          "player1": {
            "index": 1,
            "doc": null,
            "type_": "address"
          },
          "player2": {
            "index": 2,
            "doc": null,
            "type_": "address"
          },
          "player1_new_card_index": {
            "index": 3,
            "doc": " Card indices swapped (for Seal access update)",
            "type_": "u64"
          },
          "player2_new_card_index": {
            "index": 4,
            "doc": null,
            "type_": "u64"
          }
        }
      }
    },
    "ChancellorDraw": {
      "index": 10,
      "doc": " Chancellor draw",
      "attributes": [],
      "abilities": [
        "Copy",
        "Drop"
      ],
      "type_parameters": [],
      "fields": {
        "positional_fields": false,
        "fields": {
          "room_id": {
            "index": 0,
            "doc": null,
            "type_": {
              "Datatype": {
                "module": {
                  "address": "sui",
                  "name": "object"
                },
                "name": "ID",
                "type_arguments": []
              }
            }
          },
          "player": {
            "index": 1,
            "doc": null,
            "type_": "address"
          },
          "drawn_card_indices": {
            "index": 2,
            "doc": null,
            "type_": {
              "vector": "u64"
            }
          }
        }
      }
    },
    "ChancellorResolved": {
      "index": 11,
      "doc": null,
      "attributes": [],
      "abilities": [
        "Copy",
        "Drop"
      ],
      "type_parameters": [],
      "fields": {
        "positional_fields": false,
        "fields": {
          "room_id": {
            "index": 0,
            "doc": null,
            "type_": {
              "Datatype": {
                "module": {
                  "address": "sui",
                  "name": "object"
                },
                "name": "ID",
                "type_arguments": []
              }
            }
          },
          "player": {
            "index": 1,
            "doc": null,
            "type_": "address"
          },
          "kept_card_index": {
            "index": 2,
            "doc": null,
            "type_": "u64"
          },
          "returned_count": {
            "index": 3,
            "doc": null,
            "type_": "u64"
          }
        }
      }
    },
    "PendingGuardResponse": {
      "index": 12,
      "doc": null,
      "attributes": [],
      "abilities": [
        "Copy",
        "Drop"
      ],
      "type_parameters": [],
      "fields": {
        "positional_fields": false,
        "fields": {
          "room_id": {
            "index": 0,
            "doc": null,
            "type_": {
              "Datatype": {
                "module": {
                  "address": "sui",
                  "name": "object"
                },
                "name": "ID",
                "type_arguments": []
              }
            }
          },
          "attacker": {
            "index": 1,
            "doc": null,
            "type_": "address"
          },
          "target": {
            "index": 2,
            "doc": null,
            "type_": "address"
          },
          "guess": {
            "index": 3,
            "doc": null,
            "type_": "u8"
          }
        }
      }
    },
    "PendingBaronResponse": {
      "index": 13,
      "doc": null,
      "attributes": [],
      "abilities": [
        "Copy",
        "Drop"
      ],
      "type_parameters": [],
      "fields": {
        "positional_fields": false,
        "fields": {
          "room_id": {
            "index": 0,
            "doc": null,
            "type_": {
              "Datatype": {
                "module": {
                  "address": "sui",
                  "name": "object"
                },
                "name": "ID",
                "type_arguments": []
              }
            }
          },
          "attacker": {
            "index": 1,
            "doc": null,
            "type_": "address"
          },
          "attacker_card": {
            "index": 2,
            "doc": null,
            "type_": "u8"
          },
          "target": {
            "index": 3,
            "doc": null,
            "type_": "address"
          }
        }
      }
    },
    "GuardResponseReceived": {
      "index": 14,
      "doc": null,
      "attributes": [],
      "abilities": [
        "Copy",
        "Drop"
      ],
      "type_parameters": [],
      "fields": {
        "positional_fields": false,
        "fields": {
          "room_id": {
            "index": 0,
            "doc": null,
            "type_": {
              "Datatype": {
                "module": {
                  "address": "sui",
                  "name": "object"
                },
                "name": "ID",
                "type_arguments": []
              }
            }
          },
          "target": {
            "index": 1,
            "doc": null,
            "type_": "address"
          },
          "revealed_card": {
            "index": 2,
            "doc": null,
            "type_": "u8"
          },
          "guess_correct": {
            "index": 3,
            "doc": null,
            "type_": "bool"
          }
        }
      }
    },
    "TokenAwarded": {
      "index": 15,
      "doc": null,
      "attributes": [],
      "abilities": [
        "Copy",
        "Drop"
      ],
      "type_parameters": [],
      "fields": {
        "positional_fields": false,
        "fields": {
          "room_id": {
            "index": 0,
            "doc": null,
            "type_": {
              "Datatype": {
                "module": {
                  "address": "sui",
                  "name": "object"
                },
                "name": "ID",
                "type_arguments": []
              }
            }
          },
          "player": {
            "index": 1,
            "doc": null,
            "type_": "address"
          },
          "total_tokens": {
            "index": 2,
            "doc": null,
            "type_": "u8"
          },
          "reason": {
            "index": 3,
            "doc": null,
            "type_": {
              "Datatype": {
                "module": {
                  "address": "std",
                  "name": "string"
                },
                "name": "String",
                "type_arguments": []
              }
            }
          }
        }
      }
    },
    "SpyBonusCheck": {
      "index": 16,
      "doc": null,
      "attributes": [],
      "abilities": [
        "Copy",
        "Drop"
      ],
      "type_parameters": [],
      "fields": {
        "positional_fields": false,
        "fields": {
          "room_id": {
            "index": 0,
            "doc": null,
            "type_": {
              "Datatype": {
                "module": {
                  "address": "sui",
                  "name": "object"
                },
                "name": "ID",
                "type_arguments": []
              }
            }
          },
          "players_with_spy": {
            "index": 1,
            "doc": null,
            "type_": {
              "vector": "address"
            }
          },
          "bonus_awarded": {
            "index": 2,
            "doc": null,
            "type_": "bool"
          },
          "bonus_recipient": {
            "index": 3,
            "doc": null,
            "type_": {
              "Datatype": {
                "module": {
                  "address": "std",
                  "name": "option"
                },
                "name": "Option",
                "type_arguments": [
                  {
                    "phantom": false,
                    "argument": "address"
                  }
                ]
              }
            }
          }
        }
      }
    },
    "GameEnded": {
      "index": 17,
      "doc": null,
      "attributes": [],
      "abilities": [
        "Copy",
        "Drop"
      ],
      "type_parameters": [],
      "fields": {
        "positional_fields": false,
        "fields": {
          "room_id": {
            "index": 0,
            "doc": null,
            "type_": {
              "Datatype": {
                "module": {
                  "address": "sui",
                  "name": "object"
                },
                "name": "ID",
                "type_arguments": []
              }
            }
          },
          "winner": {
            "index": 1,
            "doc": null,
            "type_": "address"
          },
          "final_tokens": {
            "index": 2,
            "doc": null,
            "type_": "u8"
          },
          "prize_pool": {
            "index": 3,
            "doc": null,
            "type_": "u64"
          },
          "total_rounds": {
            "index": 4,
            "doc": null,
            "type_": "u8"
          }
        }
      }
    },
    "CommitmentCreated": {
      "index": 18,
      "doc": null,
      "attributes": [],
      "abilities": [
        "Copy",
        "Drop"
      ],
      "type_parameters": [],
      "fields": {
        "positional_fields": false,
        "fields": {
          "room_id": {
            "index": 0,
            "doc": null,
            "type_": {
              "Datatype": {
                "module": {
                  "address": "sui",
                  "name": "object"
                },
                "name": "ID",
                "type_arguments": []
              }
            }
          },
          "card_index": {
            "index": 1,
            "doc": null,
            "type_": "u64"
          },
          "commitment": {
            "index": 2,
            "doc": null,
            "type_": {
              "vector": "u8"
            }
          }
        }
      }
    },
    "CommitmentVerified": {
      "index": 19,
      "doc": null,
      "attributes": [],
      "abilities": [
        "Copy",
        "Drop"
      ],
      "type_parameters": [],
      "fields": {
        "positional_fields": false,
        "fields": {
          "room_id": {
            "index": 0,
            "doc": null,
            "type_": {
              "Datatype": {
                "module": {
                  "address": "sui",
                  "name": "object"
                },
                "name": "ID",
                "type_arguments": []
              }
            }
          },
          "card_index": {
            "index": 1,
            "doc": null,
            "type_": "u64"
          },
          "revealed_value": {
            "index": 2,
            "doc": null,
            "type_": "u8"
          },
          "verified": {
            "index": 3,
            "doc": null,
            "type_": "bool"
          }
        }
      }
    },
    "TemporaryAccessGranted": {
      "index": 20,
      "doc": null,
      "attributes": [],
      "abilities": [
        "Copy",
        "Drop"
      ],
      "type_parameters": [],
      "fields": {
        "positional_fields": false,
        "fields": {
          "room_id": {
            "index": 0,
            "doc": null,
            "type_": {
              "Datatype": {
                "module": {
                  "address": "sui",
                  "name": "object"
                },
                "name": "ID",
                "type_arguments": []
              }
            }
          },
          "viewer": {
            "index": 1,
            "doc": null,
            "type_": "address"
          },
          "card_index": {
            "index": 2,
            "doc": null,
            "type_": "u64"
          },
          "expires_turn": {
            "index": 3,
            "doc": null,
            "type_": "u64"
          }
        }
      }
    }
  },
  "enums": {}
}